dot_proxy.py
dot_proxy-0.3.0.dist-info/LICENSE
dot_proxy-0.3.0.dist-info/METADATA
dot_proxy-0.3.0.dist-info/WHEEL
dot_proxy-0.3.0.dist-info/entry_points.txt
dot_proxy-0.3.0.dist-info/top_level.txt
dot_proxy-0.3.0.dist-info/RECORD
