Metadata-Version: 2.1
Name: dot-proxy
Version: 0.3.0
Summary: DNS over TLS Proxy Server.
Author: Sergey M
License: Copyright 2024 Sergey M
Project-URL: Repository, https://github.com/s3rgeym/dot-proxy.git
Classifier: Topic :: Internet
Requires-Python: >=3.11.7
License-File: LICENSE
Provides-Extra: dev
Requires-Dist: black ; extra == 'dev'
Requires-Dist: pylint ; extra == 'dev'
Provides-Extra: test
Requires-Dist: pytest ; extra == 'test'
